{
    "author": "jessicajaniuk",
    "message": "docs: release notes for the v12.2.7 release (#43538)",
    "sha": "d2a03b153e0223f3417dcf3c74814dfe16525e27",
    "files": [
        {
            "sha": "94c18d99d1d2f5dc73586bd28ec575d22783109e",
            "filename": "CHANGELOG.md",
            "status": "modified",
            "additions": 22,
            "deletions": 0,
            "changes": 22,
            "blob_url": "https://github.com/angular/angular/blob/d2a03b153e0223f3417dcf3c74814dfe16525e27/CHANGELOG.md",
            "raw_url": "https://github.com/angular/angular/raw/d2a03b153e0223f3417dcf3c74814dfe16525e27/CHANGELOG.md",
            "contents_url": "https://api.github.com/repos/angular/angular/contents/CHANGELOG.md?ref=d2a03b153e0223f3417dcf3c74814dfe16525e27",
            "patch": "@@ -1,3 +1,25 @@\n+<a name=\"12.2.7\"></a>\n+# 12.2.7 (2021-09-22)\n+### common\n+| Commit | Type | Description |\n+| -- | -- | -- |\n+| [2bb4bf1468](https://github.com/angular/angular/commit/2bb4bf1468935a49a3d478d0cc13e7eb7fd1b98a) | fix | titlecase pipe incorrectly handling numbers ([#43476](https://github.com/angular/angular/pull/43476)) |\n+### compiler\n+| Commit | Type | Description |\n+| -- | -- | -- |\n+| [9c8a1f8a71](https://github.com/angular/angular/commit/9c8a1f8a71be9b8380afbdc61ee7ee60f24488b4) | fix | include leading whitespace in source-spans of i18n messages ([#43132](https://github.com/angular/angular/pull/43132)) |\n+### compiler-cli\n+| Commit | Type | Description |\n+| -- | -- | -- |\n+| [defb02f11e](https://github.com/angular/angular/commit/defb02f11e2bd75452e8722e1474bb230d189864) | fix | handle directives that refer to a namespaced class in a type parameter bound ([#43511](https://github.com/angular/angular/pull/43511)) |\n+### platform-browser\n+| Commit | Type | Description |\n+| -- | -- | -- |\n+| [adc7c56ede](https://github.com/angular/angular/commit/adc7c56ede7ad34a90f5ef1b878e261836b25c45) | fix | improve error message for missing animation trigger ([#41356](https://github.com/angular/angular/pull/41356)) |\n+## Special Thanks\n+Andrew Scott, Daniel Díaz, George Kalpakas, JoostK, Kristiyan Kostadinov, Mwiku, Pete Bacon Darwin, Teri Glover, Virginia Dooley, Xiaohanxu1996, dario-piotrowicz and kirjs\n+\n+\n <a name=\"13.0.0-next.6\"></a>\n # 13.0.0-next.6 (2021-09-15)\n ### animations"
        }
    ],
    "stats": {
        "total": 22,
        "additions": 22,
        "deletions": 0
    }
}