{
    "author": "cjihrig",
    "message": "esm: remove unused catch bindings\n\nPR-URL: https://github.com/nodejs/node/pull/24079\nReviewed-By: Sam Roberts <vieuxtech@gmail.com>\nReviewed-By: Wyatt Preul <wpreul@gmail.com>",
    "sha": "a64ca7139ec1c04aff033fd1c6a1cd6c6a99c015",
    "files": [
        {
            "sha": "60f1e31f94e86e5fbe7fbc2e47c5c5640c54d377",
            "filename": "lib/internal/modules/esm/loader.js",
            "status": "modified",
            "additions": 1,
            "deletions": 1,
            "changes": 2,
            "blob_url": "https://github.com/nodejs/node/blob/a64ca7139ec1c04aff033fd1c6a1cd6c6a99c015/lib%2Finternal%2Fmodules%2Fesm%2Floader.js",
            "raw_url": "https://github.com/nodejs/node/raw/a64ca7139ec1c04aff033fd1c6a1cd6c6a99c015/lib%2Finternal%2Fmodules%2Fesm%2Floader.js",
            "contents_url": "https://api.github.com/repos/nodejs/node/contents/lib%2Finternal%2Fmodules%2Fesm%2Floader.js?ref=a64ca7139ec1c04aff033fd1c6a1cd6c6a99c015",
            "patch": "@@ -80,7 +80,7 @@ class Loader {\n     if (this._resolve !== defaultResolve) {\n       try {\n         new URL(url);\n-      } catch (e) {\n+      } catch {\n         throw new ERR_INVALID_RETURN_PROPERTY(\n           'url', 'loader resolve', 'url', url\n         );"
        }
    ],
    "stats": {
        "total": 2,
        "additions": 1,
        "deletions": 1
    }
}