{
    "author": "ojeytonwilliams",
    "message": "fix: delete/reset modal - stop passing event payloads (#64618)",
    "sha": "3bdf64b4e7ed653986827aa6646a80d98fa4bac9",
    "files": [
        {
            "sha": "4f2438c73ac0194da1b57b884879f3aa1d701900",
            "filename": "client/src/components/settings/delete-modal.tsx",
            "status": "modified",
            "additions": 2,
            "deletions": 2,
            "changes": 4,
            "blob_url": "https://github.com/freeCodeCamp/freeCodeCamp/blob/3bdf64b4e7ed653986827aa6646a80d98fa4bac9/client%2Fsrc%2Fcomponents%2Fsettings%2Fdelete-modal.tsx",
            "raw_url": "https://github.com/freeCodeCamp/freeCodeCamp/raw/3bdf64b4e7ed653986827aa6646a80d98fa4bac9/client%2Fsrc%2Fcomponents%2Fsettings%2Fdelete-modal.tsx",
            "contents_url": "https://api.github.com/repos/freeCodeCamp/freeCodeCamp/contents/client%2Fsrc%2Fcomponents%2Fsettings%2Fdelete-modal.tsx?ref=3bdf64b4e7ed653986827aa6646a80d98fa4bac9",
            "patch": "@@ -10,7 +10,7 @@ import {\n } from '@freecodecamp/ui';\n \n type DeleteModalProps = {\n-  delete: () => void;\n+  delete: (x?: never) => void;\n   onHide: () => void;\n   show: boolean;\n };\n@@ -72,7 +72,7 @@ function DeleteModal(props: DeleteModalProps): JSX.Element {\n           block={true}\n           size='large'\n           variant='danger'\n-          onClick={props.delete}\n+          onClick={() => props.delete()}\n           disabled={verifyText !== t('settings.danger.verify-delete-text')}\n           type='button'\n         >"
        },
        {
            "sha": "b4304542c2d134a3f67a00c97f9a118e9eb789f2",
            "filename": "client/src/components/settings/reset-modal.tsx",
            "status": "modified",
            "additions": 2,
            "deletions": 2,
            "changes": 4,
            "blob_url": "https://github.com/freeCodeCamp/freeCodeCamp/blob/3bdf64b4e7ed653986827aa6646a80d98fa4bac9/client%2Fsrc%2Fcomponents%2Fsettings%2Freset-modal.tsx",
            "raw_url": "https://github.com/freeCodeCamp/freeCodeCamp/raw/3bdf64b4e7ed653986827aa6646a80d98fa4bac9/client%2Fsrc%2Fcomponents%2Fsettings%2Freset-modal.tsx",
            "contents_url": "https://api.github.com/repos/freeCodeCamp/freeCodeCamp/contents/client%2Fsrc%2Fcomponents%2Fsettings%2Freset-modal.tsx?ref=3bdf64b4e7ed653986827aa6646a80d98fa4bac9",
            "patch": "@@ -11,7 +11,7 @@ import {\n \n type ResetModalProps = {\n   onHide: () => void;\n-  reset: () => void;\n+  reset: (x?: never) => void;\n   show: boolean;\n };\n \n@@ -71,7 +71,7 @@ function ResetModal(props: ResetModalProps): JSX.Element {\n           size='large'\n           variant='danger'\n           disabled={verifyText !== t('settings.danger.verify-reset-text')}\n-          onClick={props.reset}\n+          onClick={() => props.reset()}\n           type='button'\n         >\n           {t('settings.danger.reset-confirm')}"
        }
    ],
    "stats": {
        "total": 8,
        "additions": 4,
        "deletions": 4
    }
}