{
    "author": "camperbot",
    "message": "chore(i18n,learn): update i18n-curriculum submodule (#55690)\n\nCo-authored-by: Mrugesh Mohapatra <1884376+raisedadead@users.noreply.github.com>",
    "sha": "628b559a75a86005ca0255109c64b8d29cd72e00",
    "files": [
        {
            "sha": "ba38d4a18111b3d837b7a7b60149f27cba7b9cf8",
            "filename": "curriculum/i18n-curriculum",
            "status": "modified",
            "additions": 1,
            "deletions": 1,
            "changes": 2,
            "blob_url": null,
            "raw_url": null,
            "contents_url": "https://api.github.com/repos/freeCodeCamp/freeCodeCamp/contents/curriculum%2Fi18n-curriculum?ref=628b559a75a86005ca0255109c64b8d29cd72e00",
            "patch": "@@ -1 +1 @@\n-Subproject commit 4751e2795178d23fc117ec90f56aaf682b8c42c6\n+Subproject commit ba38d4a18111b3d837b7a7b60149f27cba7b9cf8"
        }
    ],
    "stats": {
        "total": 2,
        "additions": 1,
        "deletions": 1
    }
}