{
    "author": "beckerhe",
    "message": "Remove redundant TENSORFLOW_USE_ROCM define.\n\nThe `TENSORFLOW_USE_ROCM=1` local define is no longer required for the `rocm_solver_context` target.\n\nPiperOrigin-RevId: 847677878",
    "sha": "23dd865ee573dbe5b112f5e1feab048df75ff227",
    "files": [
        {
            "sha": "5b01213aeb2a067d545a59d7122884de21e6b93c",
            "filename": "third_party/xla/xla/stream_executor/rocm/BUILD",
            "status": "modified",
            "additions": 0,
            "deletions": 3,
            "changes": 3,
            "blob_url": "https://github.com/tensorflow/tensorflow/blob/23dd865ee573dbe5b112f5e1feab048df75ff227/third_party%2Fxla%2Fxla%2Fstream_executor%2Frocm%2FBUILD",
            "raw_url": "https://github.com/tensorflow/tensorflow/raw/23dd865ee573dbe5b112f5e1feab048df75ff227/third_party%2Fxla%2Fxla%2Fstream_executor%2Frocm%2FBUILD",
            "contents_url": "https://api.github.com/repos/tensorflow/tensorflow/contents/third_party%2Fxla%2Fxla%2Fstream_executor%2Frocm%2FBUILD?ref=23dd865ee573dbe5b112f5e1feab048df75ff227",
            "patch": "@@ -422,9 +422,6 @@ cc_library(\n     name = \"rocm_solver_context\",\n     srcs = [\"rocm_solver_context.cc\"],\n     hdrs = [\"rocm_solver_context.h\"],\n-    local_defines = [\n-        \"TENSORFLOW_USE_ROCM=1\",\n-    ],\n     tags = [\n         \"gpu\",\n         \"manual\","
        }
    ],
    "stats": {
        "total": 3,
        "additions": 0,
        "deletions": 3
    }
}