{
    "author": "Becker-ZH",
    "message": "Remove Ignore Error\n\nPiperOrigin-RevId: 807550564",
    "sha": "8f20f9e7c75e33fd2b0c954d8559d17e91bfc6ad",
    "files": [
        {
            "sha": "b31cb4c6f9e5daa4b5f6051f1dc1faa95d807fc3",
            "filename": "third_party/xla/xla/backends/profiler/gpu/cupti_tracer.cc",
            "status": "modified",
            "additions": 1,
            "deletions": 1,
            "changes": 2,
            "blob_url": "https://github.com/tensorflow/tensorflow/blob/8f20f9e7c75e33fd2b0c954d8559d17e91bfc6ad/third_party%2Fxla%2Fxla%2Fbackends%2Fprofiler%2Fgpu%2Fcupti_tracer.cc",
            "raw_url": "https://github.com/tensorflow/tensorflow/raw/8f20f9e7c75e33fd2b0c954d8559d17e91bfc6ad/third_party%2Fxla%2Fxla%2Fbackends%2Fprofiler%2Fgpu%2Fcupti_tracer.cc",
            "contents_url": "https://api.github.com/repos/tensorflow/tensorflow/contents/third_party%2Fxla%2Fxla%2Fbackends%2Fprofiler%2Fgpu%2Fcupti_tracer.cc?ref=8f20f9e7c75e33fd2b0c954d8559d17e91bfc6ad",
            "patch": "@@ -1107,7 +1107,7 @@ absl::Status CuptiTracer::Enable(\n     return status;\n   }\n \n-  EnableActivityTracing().IgnoreError();\n+  TF_RETURN_IF_ERROR(EnableActivityTracing());\n   tsl::profiler::AnnotationStack::Enable(true);\n \n   int num_gpus_requested = xplanes.size();"
        },
        {
            "sha": "e110e0c6bbd4b3d446e39f0c579f2b9182edc2b9",
            "filename": "third_party/xla/xla/backends/profiler/gpu/device_tracer_cuda.cc",
            "status": "modified",
            "additions": 2,
            "deletions": 2,
            "changes": 4,
            "blob_url": "https://github.com/tensorflow/tensorflow/blob/8f20f9e7c75e33fd2b0c954d8559d17e91bfc6ad/third_party%2Fxla%2Fxla%2Fbackends%2Fprofiler%2Fgpu%2Fdevice_tracer_cuda.cc",
            "raw_url": "https://github.com/tensorflow/tensorflow/raw/8f20f9e7c75e33fd2b0c954d8559d17e91bfc6ad/third_party%2Fxla%2Fxla%2Fbackends%2Fprofiler%2Fgpu%2Fdevice_tracer_cuda.cc",
            "contents_url": "https://api.github.com/repos/tensorflow/tensorflow/contents/third_party%2Fxla%2Fxla%2Fbackends%2Fprofiler%2Fgpu%2Fdevice_tracer_cuda.cc?ref=8f20f9e7c75e33fd2b0c954d8559d17e91bfc6ad",
            "patch": "@@ -118,8 +118,8 @@ absl::Status GpuTracer::DoStart() {\n   for (int i = 0; i < collector_options.num_gpus; ++i) {\n     xplanes_.push_back(std::make_unique<tensorflow::profiler::XPlane>());\n   }\n-  cupti_tracer_->Enable(options_, cupti_collector_.get(), xplanes_)\n-      .IgnoreError();\n+  TF_RETURN_IF_ERROR(\n+      cupti_tracer_->Enable(options_, cupti_collector_.get(), xplanes_));\n   return absl::OkStatus();\n }\n "
        }
    ],
    "stats": {
        "total": 6,
        "additions": 3,
        "deletions": 3
    }
}