{
    "author": "Cyrilvallez",
    "message": "[loading] Fix device detection (#42323)\n\nfix",
    "sha": "4799952dca3383e577a686ca5feb25b90399d7a3",
    "files": [
        {
            "sha": "1a13ade9d4530bed419522d0b739c276865c3e65",
            "filename": "src/transformers/core_model_loading.py",
            "status": "modified",
            "additions": 1,
            "deletions": 1,
            "changes": 2,
            "blob_url": "https://github.com/huggingface/transformers/blob/4799952dca3383e577a686ca5feb25b90399d7a3/src%2Ftransformers%2Fcore_model_loading.py",
            "raw_url": "https://github.com/huggingface/transformers/raw/4799952dca3383e577a686ca5feb25b90399d7a3/src%2Ftransformers%2Fcore_model_loading.py",
            "contents_url": "https://api.github.com/repos/huggingface/transformers/contents/src%2Ftransformers%2Fcore_model_loading.py?ref=4799952dca3383e577a686ca5feb25b90399d7a3",
            "patch": "@@ -610,7 +610,7 @@ def convert_and_load_state_dict_in_model(\n     tp_plan = tp_plan or {}\n     device_map = device_map or {\"\": \"cpu\"}\n     device_map_regex = re.compile(\n-        \"|\".join(rf\"({k})\" for k in sorted(device_map.keys(), key=lambda x: x.count(\".\"), reverse=True))\n+        \"|\".join(rf\"({k})\" for k in sorted(device_map.keys(), key=lambda x: (x.count(\".\"), len(x)), reverse=True))\n     )\n     dtype_plan = dtype_plan or {}\n     weight_mapping = weight_mapping or []"
        }
    ],
    "stats": {
        "total": 2,
        "additions": 1,
        "deletions": 1
    }
}