{
    "author": "huozhi",
    "message": "[dev-overlay] do not force hide scrollbar (#76504)",
    "sha": "9fd557ff8e6e802e2df5cb48654da2401acc05ea",
    "files": [
        {
            "sha": "039a49d3d74ac3b88d5e6fcbea6fdabecf74ac81",
            "filename": "packages/next/src/client/components/react-dev-overlay/ui/components/dialog/styles.ts",
            "status": "modified",
            "additions": 0,
            "deletions": 3,
            "changes": 3,
            "blob_url": "https://github.com/vercel/next.js/blob/9fd557ff8e6e802e2df5cb48654da2401acc05ea/packages%2Fnext%2Fsrc%2Fclient%2Fcomponents%2Freact-dev-overlay%2Fui%2Fcomponents%2Fdialog%2Fstyles.ts",
            "raw_url": "https://github.com/vercel/next.js/raw/9fd557ff8e6e802e2df5cb48654da2401acc05ea/packages%2Fnext%2Fsrc%2Fclient%2Fcomponents%2Freact-dev-overlay%2Fui%2Fcomponents%2Fdialog%2Fstyles.ts",
            "contents_url": "https://api.github.com/repos/vercel/next.js/contents/packages%2Fnext%2Fsrc%2Fclient%2Fcomponents%2Freact-dev-overlay%2Fui%2Fcomponents%2Fdialog%2Fstyles.ts?ref=9fd557ff8e6e802e2df5cb48654da2401acc05ea",
            "patch": "@@ -28,9 +28,6 @@ const styles = `\n     outline: none;\n     overflow: hidden;\n   }\n-  [data-nextjs-dialog]::-webkit-scrollbar {\n-    display: none;\n-  }\n \n   ${\n     '' /* Place overflow: hidden on this so we can break out from [data-nextjs-dialog] */"
        }
    ],
    "stats": {
        "total": 3,
        "additions": 0,
        "deletions": 3
    }
}