{
    "author": "claudep",
    "message": "Fixed #18301 -- Fixed url name in password reset example.\n\nThanks nicknnn for the report.",
    "sha": "0611e1fed2308ad5613cffd3629dfa5a97248dff",
    "files": [
        {
            "sha": "c3a2636aaf757e64847d58c0b09ae7305414fe13",
            "filename": "docs/topics/auth.txt",
            "status": "modified",
            "additions": 1,
            "deletions": 1,
            "changes": 2,
            "blob_url": "https://github.com/django/django/blob/0611e1fed2308ad5613cffd3629dfa5a97248dff/docs%2Ftopics%2Fauth.txt",
            "raw_url": "https://github.com/django/django/raw/0611e1fed2308ad5613cffd3629dfa5a97248dff/docs%2Ftopics%2Fauth.txt",
            "contents_url": "https://api.github.com/repos/django/django/contents/docs%2Ftopics%2Fauth.txt?ref=0611e1fed2308ad5613cffd3629dfa5a97248dff",
            "patch": "@@ -1242,7 +1242,7 @@ includes a few other useful built-in views located in\n     .. code-block:: html+django\n \n         Someone asked for password reset for email {{ email }}. Follow the link below:\n-        {{ protocol}}://{{ domain }}{% url 'auth_password_reset_confirm' uidb36=uid token=token %}\n+        {{ protocol}}://{{ domain }}{% url 'password_reset_confirm' uidb36=uid token=token %}\n \n     The same template context is used for subject template. Subject must be\n     single line plain text string."
        }
    ],
    "stats": {
        "total": 2,
        "additions": 1,
        "deletions": 1
    }
}