{
    "author": "PaulMcMillan",
    "message": "Fix broken test introduced by r17526.\n\n\ngit-svn-id: http://code.djangoproject.com/svn/django/trunk@17527 bcc190cf-cafb-0310-a4f2-bffc1f526a37",
    "sha": "06da2be00fb371a27e10ce37821643914c93adc6",
    "files": [
        {
            "sha": "beccfc5d0771ee6f959cfb285b5c62a11f0a2236",
            "filename": "django/contrib/auth/tests/tokens.py",
            "status": "modified",
            "additions": 3,
            "deletions": 2,
            "changes": 5,
            "blob_url": "https://github.com/django/django/blob/06da2be00fb371a27e10ce37821643914c93adc6/django%2Fcontrib%2Fauth%2Ftests%2Ftokens.py",
            "raw_url": "https://github.com/django/django/raw/06da2be00fb371a27e10ce37821643914c93adc6/django%2Fcontrib%2Fauth%2Ftests%2Ftokens.py",
            "contents_url": "https://api.github.com/repos/django/django/contents/django%2Fcontrib%2Fauth%2Ftests%2Ftokens.py?ref=06da2be00fb371a27e10ce37821643914c93adc6",
            "patch": "@@ -59,5 +59,6 @@ def test_date_length(self):\n         p0 = PasswordResetTokenGenerator()\n \n         # This will put a 14-digit base36 timestamp into the token, which is too large.\n-        tk1 = p0._make_token_with_timestamp(user, 175455491841851871349)\n-        self.assertFalse(p0.check_token(user, tk1))\n+        self.assertRaises(ValueError,\n+                          p0._make_token_with_timestamp,\n+                          user, 175455491841851871349)"
        }
    ],
    "stats": {
        "total": 5,
        "additions": 3,
        "deletions": 2
    }
}