{
    "author": "aaugustin",
    "message": "Added missing method in the dummy database backend.",
    "sha": "25ce177e66fb0e88a39806f5a493e03f1801775a",
    "files": [
        {
            "sha": "c59f037a2766dcc09fb0d0f01947141e8d278f2b",
            "filename": "django/db/backends/dummy/base.py",
            "status": "modified",
            "additions": 3,
            "deletions": 0,
            "changes": 3,
            "blob_url": "https://github.com/django/django/blob/25ce177e66fb0e88a39806f5a493e03f1801775a/django%2Fdb%2Fbackends%2Fdummy%2Fbase.py",
            "raw_url": "https://github.com/django/django/raw/25ce177e66fb0e88a39806f5a493e03f1801775a/django%2Fdb%2Fbackends%2Fdummy%2Fbase.py",
            "contents_url": "https://api.github.com/repos/django/django/contents/django%2Fdb%2Fbackends%2Fdummy%2Fbase.py?ref=25ce177e66fb0e88a39806f5a493e03f1801775a",
            "patch": "@@ -71,3 +71,6 @@ def __init__(self, *args, **kwargs):\n         self.creation = DatabaseCreation(self)\n         self.introspection = DatabaseIntrospection(self)\n         self.validation = BaseDatabaseValidation(self)\n+\n+    def is_usable(self):\n+        return True"
        }
    ],
    "stats": {
        "total": 3,
        "additions": 3,
        "deletions": 0
    }
}