{
    "author": "claudep",
    "message": "Minor cleanups in templates test imports",
    "sha": "335a060fa6a919fc5eb1ff22315f9b3ae44438b7",
    "files": [
        {
            "sha": "1eca735612cb56c3f74a28f7e0da550460b63517",
            "filename": "tests/regressiontests/templates/tests.py",
            "status": "modified",
            "additions": 2,
            "deletions": 6,
            "changes": 8,
            "blob_url": "https://github.com/django/django/blob/335a060fa6a919fc5eb1ff22315f9b3ae44438b7/tests%2Fregressiontests%2Ftemplates%2Ftests.py",
            "raw_url": "https://github.com/django/django/raw/335a060fa6a919fc5eb1ff22315f9b3ae44438b7/tests%2Fregressiontests%2Ftemplates%2Ftests.py",
            "contents_url": "https://api.github.com/repos/django/django/contents/tests%2Fregressiontests%2Ftemplates%2Ftests.py?ref=335a060fa6a919fc5eb1ff22315f9b3ae44438b7",
            "patch": "@@ -19,10 +19,9 @@\n     from urlparse import urljoin\n \n from django import template\n-from django.template import (base as template_base, Context, RequestContext,\n-    Template)\n from django.core import urlresolvers\n-from django.template import loader\n+from django.template import (base as template_base, loader, Context,\n+    RequestContext, Template, TemplateSyntaxError)\n from django.template.loaders import app_directories, filesystem, cached\n from django.test import RequestFactory, TestCase\n from django.test.utils import (setup_test_template_loader,\n@@ -365,8 +364,6 @@ def test_token_smart_split(self):\n     @override_settings(SETTINGS_MODULE=None, TEMPLATE_DEBUG=True)\n     def test_url_reverse_no_settings_module(self):\n         # Regression test for #9005\n-        from django.template import Template, Context\n-\n         t = Template('{% url will_not_match %}')\n         c = Context()\n         with self.assertRaises(urlresolvers.NoReverseMatch):\n@@ -417,7 +414,6 @@ def test_no_wrapped_exception(self):\n \n     def test_invalid_block_suggestion(self):\n         # See #7876\n-        from django.template import Template, TemplateSyntaxError\n         try:\n             t = Template(\"{% if 1 %}lala{% endblock %}{% endif %}\")\n         except TemplateSyntaxError as e:"
        }
    ],
    "stats": {
        "total": 8,
        "additions": 2,
        "deletions": 6
    }
}